gcloud/aio/auth/__init__.py
gcloud/aio/auth/build_constants.py
gcloud/aio/auth/iam.py
gcloud/aio/auth/py.typed
gcloud/aio/auth/session.py
gcloud/aio/auth/token.py
gcloud/aio/auth/utils.py
gcloud/aio/py.typed
gcloud/py.typed
gcloud_aio_auth-5.4.0.dist-info/LICENSE
gcloud_aio_auth-5.4.0.dist-info/METADATA
gcloud_aio_auth-5.4.0.dist-info/WHEEL
gcloud_aio_auth-5.4.0.dist-info/RECORD
