Metadata-Version: 2.3
Name: gcloud-aio-auth
Version: 5.4.0
Summary: Python Client for Google Cloud Auth
License: MIT
Author: Vi Engineering
Author-email: voiceai-eng@dialpad.com
Requires-Python: >=3.9,<4.0
Classifier: Development Status :: 5 - Production/Stable
Classifier: Intended Audience :: Developers
Classifier: License :: OSI Approved :: MIT License
Classifier: Operating System :: OS Independent
Classifier: Programming Language :: Python :: 3
Classifier: Programming Language :: Python :: 3.9
Classifier: Programming Language :: Python :: 3.10
Classifier: Programming Language :: Python :: 3.11
Classifier: Programming Language :: Python :: 3.12
Classifier: Programming Language :: Python :: 3.13
Classifier: Topic :: Internet
Requires-Dist: aiohttp (>=3.9.0,<4.0.0)
Requires-Dist: backoff (>=1.0.0,<3.0.0)
Requires-Dist: chardet (>=2.0,<6.0)
Requires-Dist: cryptography (>=2.0.0,<47.0.0)
Requires-Dist: pyjwt (>=1.5.3,<3.0.0)
Project-URL: Repository, https://github.com/talkiq/gcloud-aio
